solo_epd_loader/__init__.py
solo_epd_loader/_version.py
solo_epd_loader/version.py
solo_epd_loader/contamination_matrices/EPT_ion_contamination_matrix_sun.dat
solo_epd_loader/data/test/l2/epd/ept/solo_L2_epd-ept-asun-rates_20200603_V02.cdf
solo_epd_loader/data/test/l2/epd/ept/solo_L2_epd-ept-north-rates_20200603_V02.cdf
solo_epd_loader/data/test/l2/epd/ept/solo_L2_epd-ept-south-rates_20200603_V02.cdf
solo_epd_loader/data/test/l2/epd/ept/solo_L2_epd-ept-sun-rates_20200603_V02.cdf
solo_epd_loader/tests/__init__.py
solo_epd_loader/tests/tests.py
solo_epd_loader-0.4.3.dist-info/licenses/LICENSE.rst
solo_epd_loader-0.4.3.dist-info/METADATA
solo_epd_loader-0.4.3.dist-info/WHEEL
solo_epd_loader-0.4.3.dist-info/top_level.txt
solo_epd_loader-0.4.3.dist-info/RECORD
