Metadata-Version: 2.4
Name: solo_epd_loader
Version: 0.4.3
Summary: Data loader for Solar Orbiter/EPD energetic charged particle sensors EPT, HET, and STEP.
Author-email: Jan Gieseler <jan.gieseler@utu.fi>
License: Copyright (c) 2022, Jan Gieseler
Project-URL: repository, https://github.com/jgieseler/solo-epd-loader
Classifier: Intended Audience :: Science/Research
Classifier: License :: OSI Approved :: BSD License
Classifier: Natural Language :: English
Classifier: Operating System :: OS Independent
Classifier: Programming Language :: Python
Classifier: Programming Language :: Python :: 3.9
Classifier: Programming Language :: Python :: 3.10
Classifier: Programming Language :: Python :: 3.11
Classifier: Programming Language :: Python :: 3.12
Classifier: Programming Language :: Python :: 3.13
Classifier: Topic :: Scientific/Engineering :: Physics
Requires-Python: >=3.9
License-File: LICENSE.rst
Requires-Dist: astropy
Requires-Dist: cdflib
Requires-Dist: drms
Requires-Dist: h5netcdf
Requires-Dist: lxml
Requires-Dist: matplotlib
Requires-Dist: numpy
Requires-Dist: pandas
Requires-Dist: requests
Requires-Dist: sunpy>=4.1.0
Requires-Dist: tqdm
Requires-Dist: zeep
Provides-Extra: test
Requires-Dist: pytest; extra == "test"
Requires-Dist: pytest-doctestplus; extra == "test"
Requires-Dist: pytest-cov; extra == "test"
Provides-Extra: docs
Requires-Dist: sphinx; extra == "docs"
Requires-Dist: sphinx-automodapi; extra == "docs"
Dynamic: license-file
